fragment_api_lib/__init__.py
fragment_api_lib/client.py
fragment_api_lib/exceptions.py
fragment_api_lib/models.py
fragment_api_lib-1.0.1.dist-info/LICENSE
fragment_api_lib-1.0.1.dist-info/METADATA
fragment_api_lib-1.0.1.dist-info/WHEEL
fragment_api_lib-1.0.1.dist-info/top_level.txt
fragment_api_lib-1.0.1.dist-info/RECORD
