Metadata-Version: 2.2
Name: fragment-api-lib
Version: 1.0.1
Summary: 🧩 Simple API client wrapper for Fragment, purchase of Telegram Stars & Premium
Author-email: NightStrang6r <a@nightstranger.space>
License: GNU General Public License v3.0 or later
Project-URL: Homepage, https://github.com/NightStrang6r/fragment-api-lib
Classifier: Programming Language :: Python :: 3.8
Classifier: Operating System :: OS Independent
Requires-Python: >=3.8
License-File: LICENSE
Requires-Dist: requests>=2.31.0
